em_stitch/__init__.py
em_stitch/lens_correction/__init__.py
em_stitch/lens_correction/lens_correction_solver.py
em_stitch/lens_correction/mesh_and_solve_transform.py
em_stitch/lens_correction/schemas.py
em_stitch/lens_correction/utils.py
em_stitch/montage/__init__.py
em_stitch/montage/meta_to_collection.py
em_stitch/montage/montage_solver.py
em_stitch/montage/schemas.py
em_stitch/plots/__init__.py
em_stitch/plots/lens_quiver_plots.py
em_stitch/plots/montage_plots.py
em_stitch/plots/schemas.py
em_stitch/plots/view_matches.py
em_stitch/utils/__init__.py
em_stitch/utils/generate_EM_tilespecs_from_metafile.py
em_stitch/utils/schemas.py
em_stitch/utils/utils.py
em_stitch/viz/__init__.py
em_stitch/viz/schemas.py
em_stitch/viz/set_permissions.py
em_stitch/viz/set_update_upload.py
em_stitch/viz/update_urls.py
em_stitch/viz/upload_to_render.py
em_stitch-0.3.4.dist-info/LICENSE
em_stitch-0.3.4.dist-info/METADATA
em_stitch-0.3.4.dist-info/WHEEL
em_stitch-0.3.4.dist-info/top_level.txt
em_stitch-0.3.4.dist-info/RECORD
