Metadata-Version: 2.1
Name: em-stitch
Version: 0.3.4
Summary: a python package for stitching EM images
Home-page: https://github.com/AllenInstitute/em_stitch
Author-email: danielk@alleninstitute.org
License: UNKNOWN
Platform: UNKNOWN
License-File: LICENSE
Requires-Dist: argschema (<2.0)
Requires-Dist: bigfeta (>=1.0.3)
Requires-Dist: marshmallow (<3.0)
Requires-Dist: numpy (>=1.13)
Requires-Dist: opencv-python
Requires-Dist: render-python (>=2.2.0)
Requires-Dist: scipy (>=1.2.1)
Requires-Dist: triangle
